Workbook

Sheet Contexto
D4: Proyecto llave en mano BSK Mesa Digital
D6: Para el proyecto completo se consideran los sueldos de 3 trabajadores los cuales son, 1 SCRUM master, 1 Desarrollador, 1 QA más algunos serivicios basicos tales como, luz, agua, internet y transporte
D8: El proyecto tiene una duración estimada de 14 meses, distribuidos en 2 meses de desarrollo y 12 meses correspondientes al contrato de mantención y soporte. Durante los primeros 3 meses se recibirán los ingresos asociados a la totalidad de los sueldos del equipo de desarrollo, incluyendo además la primera mensualidad del contrato de mantención y soporte, la cual se facturará en el mes 3. En el mes 4 se completará el pago correspondiente al desarrollo mediante una cuota de mayor monto, dado que incorpora gran parte de la utilidad del proyecto. A partir de dicho mes, también continuará el ingreso regular de la mensualidad del contrato de mantención y soporte. Desde el mes 5 en adelante, los ingresos corresponderán exclusivamente a las cuotas mensuales del contrato de mantención y soporte, operando con normalidad según lo planificado.
D12: Para el calculo del VAN, se considera el supuesto de que el proyecto se vende con un porcentaje de utilidad del 60% por sobre el costo del proyecto. Para el calculo del TIR se considera que no existe una inversion inicial significativa por lo cual el TIR no ayuda mucho a medir la viabilidad del proyecto se recomienda discrecion con esta metrica.

Sheet Plan De Costos
A3: Trabajadores | B3: Personal | C3: Pago x hora | D3: Cantidad horas | E3: Total | F3: Observación | H3: Item | I3: Total
A4: Scrum Master | B4: Kevin Jimenez | C4: 11812 | D4: 325 | E4: =C4*D4 -> 3838900 | F4: - | H4: =A3 -> Trabajadores | I4: =SUM(E4:E6) -> 9688900
A5: Desarrollador | B5: Sebastian Cortes | C5: 9500 | D5: =325 -> 325 | E5: =C5*D5 -> 3087500 | F5: No incluye el contrato de mantencion | H5: =A8 -> Gastos generales | I5: =SUM(D9:D12) -> 231580
A6: QA | B6: Benjamin Urra | C6: 8500 | D6: 325 | E6: =C6*D6 -> 2762500 | F6: - | H6: =A14 -> Contrato de mantención | I6: =E15 -> 1900000
H7: TOTAL GENERAL | I7: =SUM(I4:I6) -> 11820480
A8: Gastos generales | B8: Precio unitario | C8: Cantidad de meses | D8: Total | E8: Observacion | I8: =I7*1.6 -> 18912768
A9: Agua | B9: 10000 | C9: 2 | D9: =B9*C9 -> 20000 | E9: Consumo de agua total entre los 3 colaboradores
A10: Internet | B10: 28000 | C10: 2 | D10: =B10*C10 -> 56000 | E10: Consumo de internet atotal entre los 3 colaboradores
A11: Transporte | B11: 24000 | C11: 2 | D11: =C11*B11 -> 48000 | E11: Tasa de transporte total utilizada entre los 3 colaboradores
A12: Luz | B12: 220 | C12: =(0.5*326)*3 -> 489 | D12: =B12*C12 -> 107580 | E12: Horas totales todos los trabajadores
A14: Contrato de mantención | B14: Personal | C14: Pago x hora | D14: Cantidad horas | E14: Total | F14: Observación
A15: Mantencion y soporte | B15: Sebastian Cortes | C15: 9500 | D15: 200 | E15: =C15*D15 -> 1900000 | F15: Costo de los sueldos del contrato de mantención

Sheet Flujo de caja
A1: Antedecentes | B1: Costos neto | C1: Costo con utilidad | E1: % de Ganacia
A2: Sueldos | B2: ='Plan De Costos'!I4 -> 9688900 | C2: =B2*(E2+100%) -> 15502240 | E2: 0.6
A3: Contrato de mantención | B3: ='Plan De Costos'!I6 -> 1900000 | C3: =B3*(E2+100%) -> 3040000
A4: Gastos generales | B4: ='Plan De Costos'!I5 -> 231580 | C4: =B4*(E2+100%) -> 370528
A5: Total | B5: =SUM(B2:B4) -> 11820480 | C5: =SUM(C2:C4) -> 18912768
A8: Egresos | B8: Mes 0 | C8: Mes 1 | D8: Mes 2 | E8: Mes 3 | F8: Mes 4 | G8: Mes 5 | H8: Mes 6 | I8: Mes 7 | J8: Mes 8 | K8: Mes 9 | L8: Mes 10 | M8: Mes 11 | N8: Mes 12 | O8: Mes 13 | P8: Mes 14 | Q8: Total
A9: Sueldos | B9: 0 | C9: =B2/3 -> 3229633.3 | D9: =B2/3 -> 3229633.3 | E9: =B2/3 -> 3229633.3 | F9: =B3/12 -> 158333.33 | G9: =B3/12 -> 158333.33 | H9: =B3/12 -> 158333.33 | I9: =B3/12 -> 158333.33 | J9: =B3/12 -> 158333.33 | K9: =B3/12 -> 158333.33 | L9: =B3/12 -> 158333.33 | M9: =B3/12 -> 158333.33 | N9: =B3/12 -> 158333.33 | O9: =B3/12 -> 158333.33 | P9: =B3/12 -> 158333.33 | Q9: =SUM(C9:P9) -> 11430567
A10: Gastos Generales | B10: 0 | C10: ='Plan De Costos'!I5/3 -> 77193.333 | D10: ='Plan De Costos'!I5/3 -> 77193.333 | E10: ='Plan De Costos'!I5/3 -> 77193.333 | F10: 0 | G10: 0 | H10: 0 | I10: 0 | J10: 0 | K10: 0 | L10: 0 | M10: 0 | N10: 0 | O10: 0 | P10: 0 | Q10: =SUM(C10:P10) -> 231580
A11: Total egresos | B11: =SUM(B9:B10) -> 0 | C11: =SUM(C9:C10) -> 3306826.7 | D11: =SUM(D9:D10) -> 3306826.7 | E11: =SUM(E9:E10) -> 3306826.7 | F11: =SUM(F9:F10) -> 158333.33 | G11: =SUM(G9:G10) -> 158333.33 | H11: =SUM(H9:H10) -> 158333.33 | I11: =SUM(I9:I10) -> 158333.33 | ... P11: =SUM(P9:P10) -> 158333.33 | Q11: =SUM(C11:P11) -> 11662147
A14: Ingresos | B14: Mes 0 | C14: Mes 1 | D14: Mes 2 | E14: Mes 3 | F14: Mes 4 | G14: Mes 5 | H14: Mes 6 | I14: Mes 7 | J14: Mes 8 | K14: Mes 9 | L14: Mes 10 | M14: Mes 11 | N14: Mes 12 | O14: Mes 13 | P14: Mes 14
A15: Sueldos | B15: 0 | C15: =B2/3 -> 3229633.3 | D15: =B2/3 -> 3229633.3 | E15: =B2/3 -> 3229633.3 | F15: =C2-B2 -> 5813340 | G15: =0 -> 0 | H15: =0 -> 0 | I15: =0 -> 0 | J15: =0 -> 0 | K15: =0 -> 0 | L15: =0 -> 0 | M15: =0 -> 0 | N15: =0 -> 0 | ... P15: =0 -> 0
A16: Contrato de mantencion | B16: 0 | C16: 0 | D16: 0 | E16: =C3/12 -> 253333.33 | F16: =C3/12 -> 253333.33 | G16: =C3/12 -> 253333.33 | H16: =C3/12 -> 253333.33 | I16: =C3/12 -> 253333.33 | J16: =C3/12 -> 253333.33 | K16: =C3/12 -> 253333.33 | L16: =C3/12 -> 253333.33 | M16: =C3/12 -> 253333.33 | N16: =C3/12 -> 253333.33 | O16: =C3/12 -> 253333.33 | P16: =C3/12 -> 253333.33
A17: Total ingresos | B17: 0 | C17: =SUM(C15:C16) -> 3229633.3 | D17: =SUM(D15:D16) -> 3229633.3 | E17: =SUM(E15:E16) -> 3482966.7 | F17: =SUM(F15:F16) -> 6066673.3 | G17: =SUM(G15:G16) -> 253333.33 | H17: =SUM(H15:H16) -> 253333.33 | I17: =SUM(I15:I16) -> 253333.33 | J17: =SUM(J15:J16) -> 253333.33 | ... P17: =SUM(P15:P16) -> 253333.33
A19: Flujo | B19: =B17-B11 -> 0 | C19: =C17-C11 -> -77193.333 | D19: =D17-D11 -> -77193.333 | E19: =E17-E11 -> 176140 | F19: =F17-F11 -> 5908340 | G19: =G17-G11 -> 95000 | H19: =H17-H11 -> 95000 | I19: =I17-I11 -> 95000 | ... P19: =P17-P11 -> 95000
A22: Resumen
A23: Valor del proyecto | B23: =B5 -> 11820480
A24: % de Ganacia | B24: 0.6
A25: Precio de venta | B25: =C5 -> 18912768
A26: Utilidad | B26: =B25-B23 -> 7092288
A27: Tasa | B27: 0.08
A28: VAN | B28: {=NPV(B27,B19:P19)} -> 4456968.7 | C28: =IF(B28>0,"==> Proyecto viable","==> Proyecto no viable") -> ==> Proyecto viable
A29: TIR | B29: =IRR(B19:P19) -> 3.1099085 | C29: Nota: La tasa interna de retorno se vuelve inestable al no haber una inversion inicial considerable por lo cual seria mas correcto no considerar la metrica para este tipo de flujo
